esem/__init__.py
esem/abc_sampler.py
esem/data_processors.py
esem/emulator.py
esem/model_adaptor.py
esem/sampler.py
esem/utils.py
esem/wrappers.py
tests/__init__.py
tests/mock.py
tests/test_abc_sampler.py
tests/test_data_processors.py
tests/test_emulator.py
tests/test_gp_model.py
tests/test_mcmc_sampler.py
tests/test_nn_model.py
tests/test_rf_model.py
tests/test_utils.py
tests/test_wrappers.py
ESEm-1.1.0.dist-info/LICENSE
ESEm-1.1.0.dist-info/METADATA
ESEm-1.1.0.dist-info/WHEEL
ESEm-1.1.0.dist-info/top_level.txt
ESEm-1.1.0.dist-info/RECORD
